pyvkbot/Bot.py
pyvkbot/Exceptions.py
pyvkbot/Keyboard.py
pyvkbot/Types.py
pyvkbot/__init__.py
pyvkbot-2.0.5.dist-info/LICENSE.md
pyvkbot-2.0.5.dist-info/METADATA
pyvkbot-2.0.5.dist-info/WHEEL
pyvkbot-2.0.5.dist-info/RECORD
