Metadata-Version: 2.1
Name: pyvkbot
Version: 2.0.5
Summary: Package for creating vk bots
Author: zeph1rr
Author-email: grianton535@gmail.com
Requires-Python: >=3.10,<4.0
Classifier: Programming Language :: Python :: 3
Classifier: Programming Language :: Python :: 3.10
Classifier: Programming Language :: Python :: 3.11
Requires-Dist: loguru (>=0.7.0,<0.8.0)
Requires-Dist: requests (>=2.28.2,<3.0.0)
Requires-Dist: vk-api (>=11.9.9,<12.0.0)
